spyboat/__init__.py
spyboat/datasets.py
spyboat/io.py
spyboat/plotting.py
spyboat/processing.py
spyboat/util.py
spyboat/test_data/two_sines.tif
spyboat-0.1.2.dist-info/LICENSE
spyboat-0.1.2.dist-info/WHEEL
spyboat-0.1.2.dist-info/METADATA
spyboat-0.1.2.dist-info/RECORD
