Metadata-Version: 2.1
Name: spyboat
Version: 0.1.2
Summary: SpyBOAT - Spatial pyBOAT 
Home-page: https://github.com/tensionhead/SpyBOAT
Author: Gregor Mönke
Author-email: tensionheadx@gmail.com
Requires-Python: >=3.6
Classifier: License :: OSI Approved :: GNU General Public License v3 or later (GPLv3+)
Classifier: Programming Language :: Python :: 3
Requires-Dist: numpy >=1.18
Requires-Dist: matplotlib >=3.1
Requires-Dist: scikit-image >=0.14.0
Requires-Dist: pyboat >=0.8.22
